{
    "ingredients": [
        {
            "tag": "cobblecuisine:red_group3"
        },
        {
            "item": "minecraft:milk_bucket"
        },
        {
            "item": "minecraft:glass_bottle"
        },
        {
            "tag": "cobblecuisine:purple_group3"
        },
        {
            "item": "minecraft:diamond"
        },
        {
            "item": "cobblemon:power_herb"
        },
        {
            "tag": "cobblemon:type_gems"
        }
    ],
    "result": {
        "count": 1,
        "id": "cobblecuisine:deluxe_jewel_shake"
    },
    "type": "minecraft:crafting_shapeless"
}